polarfrost/__init__.py
polarfrost/clustering.py
polarfrost/mondrian.py
polarfrost/py.typed
polarfrost/tests/__init__.py
polarfrost-0.2.1.dist-info/METADATA
polarfrost-0.2.1.dist-info/WHEEL
polarfrost-0.2.1.dist-info/top_level.txt
polarfrost-0.2.1.dist-info/RECORD
